kemksp/__init__.py
kemksp/config.json
kemksp/kemterminal.py
kem4ksp-0.2.0.dist-info/LICENSE.md
kem4ksp-0.2.0.dist-info/METADATA
kem4ksp-0.2.0.dist-info/WHEEL
kem4ksp-0.2.0.dist-info/entry_points.txt
kem4ksp-0.2.0.dist-info/top_level.txt
kem4ksp-0.2.0.dist-info/RECORD
